{"212655266224@s.whatsapp.net":true,"212697239364@s.whatsapp.net":true,"212713879113@s.whatsapp.net":true,"212607544250@s.whatsapp.net":true,"212645722663@s.whatsapp.net":true,"212717450923@s.whatsapp.net":true,"212623162841@s.whatsapp.net":true,"212655052135@s.whatsapp.net":true,"212606092492@s.whatsapp.net":true,"212722548734@s.whatsapp.net":true,"212717724029@s.whatsapp.net":true,"212717724029:10@s.whatsapp.net":true,"212608760333@s.whatsapp.net":true,"212655176449@s.whatsapp.net":true,"212609223645@s.whatsapp.net":true,"212714616814@s.whatsapp.net":true,"212617296819@s.whatsapp.net":true,"212656131605@s.whatsapp.net":true,"212646311395@s.whatsapp.net":true,"212656254883@s.whatsapp.net":true,"212709669513@s.whatsapp.net":true,"212656785482@s.whatsapp.net":true,"212600473417@s.whatsapp.net":true,"212703543090@s.whatsapp.net":true,"212605637469@s.whatsapp.net":true,"212713289543@s.whatsapp.net":true,"212628190998@s.whatsapp.net":true,"212716814574@s.whatsapp.net":true,"212768379931@s.whatsapp.net":true,"5355990034@s.whatsapp.net":true,"212724117548@s.whatsapp.net":true,"212694208839@s.whatsapp.net":true,"212778812427@s.whatsapp.net":true,"212605828642@s.whatsapp.net":true,"212717957725@s.whatsapp.net":true,"212627218137@s.whatsapp.net":true,"212603721372@s.whatsapp.net":true,"212626841158@s.whatsapp.net":true,"212721114383@s.whatsapp.net":true,"212680496630@s.whatsapp.net":true,"212720609810@s.whatsapp.net":true,"212600244679@s.whatsapp.net":true,"212766536555@s.whatsapp.net":true,"212632161545@s.whatsapp.net":true,"212719604410@s.whatsapp.net":true,"212667853739@s.whatsapp.net":true,"212684502035@s.whatsapp.net":true,"212632398560@s.whatsapp.net":true,"212659192871@s.whatsapp.net":true,"212716669813@s.whatsapp.net":true,"212652754827@s.whatsapp.net":true,"212688817903@s.whatsapp.net":true,"212629987962@s.whatsapp.net":true,"212713600082@s.whatsapp.net":true,"212712159921@s.whatsapp.net":true,"212630605045@s.whatsapp.net":true,"212724021505@s.whatsapp.net":true,"212721218616@s.whatsapp.net":true,"212605720685@s.whatsapp.net":true,"212656566292@s.whatsapp.net":true,"212608618123@s.whatsapp.net":true,"212681499824@s.whatsapp.net":true,"212638659678@s.whatsapp.net":true,"212603164608@s.whatsapp.net":true,"212721971949@s.whatsapp.net":true,"212626297343@s.whatsapp.net":true,"212710372444@s.whatsapp.net":true,"212635230955@s.whatsapp.net":true,"212699170357@s.whatsapp.net":true,"212713513431@s.whatsapp.net":true,"212646239024@s.whatsapp.net":true,"212638453226@s.whatsapp.net":true,"212638453226:6@s.whatsapp.net":true,"212610567655@s.whatsapp.net":true,"212638803905@s.whatsapp.net":true,"212627229972@s.whatsapp.net":true,"212601798414@s.whatsapp.net":true,"212627435644@s.whatsapp.net":true,"212602687725@s.whatsapp.net":true,"212680159392@s.whatsapp.net":true,"212719837288@s.whatsapp.net":true,"212712481968@s.whatsapp.net":true,"212627230913@s.whatsapp.net":true,"212605002776@s.whatsapp.net":true,"212627351530@s.whatsapp.net":true,"212610213700@s.whatsapp.net":true,"212631927482@s.whatsapp.net":true,"212625670974@s.whatsapp.net":true,"212603893445@s.whatsapp.net":true,"212634211017@s.whatsapp.net":true,"212626240236@s.whatsapp.net":true,"212619346582@s.whatsapp.net":true,"212604195012@s.whatsapp.net":true,"212643443856@s.whatsapp.net":true,"212630025101@s.whatsapp.net":true,"212772191569@s.whatsapp.net":true,"212610181521@s.whatsapp.net":true,"212771912469@s.whatsapp.net":true,"212690673257@s.whatsapp.net":true,"212630484782@s.whatsapp.net":true,"212778805063@s.whatsapp.net":true,"212710137958@s.whatsapp.net":true,"212630286479@s.whatsapp.net":true,"212694513734@s.whatsapp.net":true,"212607345115@s.whatsapp.net":true,"212712602847@s.whatsapp.net":true,"212630779832@s.whatsapp.net":true,"212662112758@s.whatsapp.net":true,"212672969747@s.whatsapp.net":true,"212689601041@s.whatsapp.net":true,"212617264970@s.whatsapp.net":true,"212780215500@s.whatsapp.net":true,"212601918649@s.whatsapp.net":true,"212774359771@s.whatsapp.net":true,"212612838187@s.whatsapp.net":true,"212644625041@s.whatsapp.net":true,"212719337166@s.whatsapp.net":true,"212693282050@s.whatsapp.net":true,"212711322783@s.whatsapp.net":true,"212779773104@s.whatsapp.net":true,"212679590577@s.whatsapp.net":true,"212765399706@s.whatsapp.net":true,"212606086170@s.whatsapp.net":true,"249909243253@s.whatsapp.net":true,"249909243253:8@s.whatsapp.net":true,"212714997583@s.whatsapp.net":true,"212697262422@s.whatsapp.net":true,"212679731357@s.whatsapp.net":true,"212607856983@s.whatsapp.net":true,"212605927929@s.whatsapp.net":true,"212608790106@s.whatsapp.net":true,"212603267034@s.whatsapp.net":true,"212620009779@s.whatsapp.net":true,"212711532940@s.whatsapp.net":true,"212706546147@s.whatsapp.net":true,"212714562962@s.whatsapp.net":true,"212762300402@s.whatsapp.net":true,"212641958856@s.whatsapp.net":true,"212687896808@s.whatsapp.net":true,"212601604570@s.whatsapp.net":true,"212604372325@s.whatsapp.net":true,"212705229779@s.whatsapp.net":true,"212697044187@s.whatsapp.net":true,"212665906701@s.whatsapp.net":true,"212631649704@s.whatsapp.net":true,"212652683817@s.whatsapp.net":true,"212651835651@s.whatsapp.net":true,"212644299079@s.whatsapp.net":true,"212632076207@s.whatsapp.net":true,"212650412339@s.whatsapp.net":true,"212601159847@s.whatsapp.net":true,"212640757366@s.whatsapp.net":true,"212693372799@s.whatsapp.net":true,"212629901685@s.whatsapp.net":true,"212630614372@s.whatsapp.net":true,"212633163944@s.whatsapp.net":true,"212631770961@s.whatsapp.net":true,"212696224039@s.whatsapp.net":true,"212633250361@s.whatsapp.net":true,"212717538209@s.whatsapp.net":true,"212644279741@s.whatsapp.net":true,"212663606346@s.whatsapp.net":true,"212601303406@s.whatsapp.net":true,"212647982110@s.whatsapp.net":true,"212627243500@s.whatsapp.net":true,"212681172840@s.whatsapp.net":true,"212682363962@s.whatsapp.net":true,"212675768248@s.whatsapp.net":true,"212604126992@s.whatsapp.net":true,"212632300454@s.whatsapp.net":true,"212602293654@s.whatsapp.net":true,"212687373651@s.whatsapp.net":true,"212712010057@s.whatsapp.net":true,"212721888607@s.whatsapp.net":true,"212779437002@s.whatsapp.net":true,"212631672964@s.whatsapp.net":true,"212714421104@s.whatsapp.net":true,"212600943250@s.whatsapp.net":true,"212682353431@s.whatsapp.net":true,"212778120255@s.whatsapp.net":true,"212630785206@s.whatsapp.net":true,"212647366979@s.whatsapp.net":true,"212651510604@s.whatsapp.net":true,"212605719704@s.whatsapp.net":true,"212628994630@s.whatsapp.net":true,"212712212336@s.whatsapp.net":true,"212711541843@s.whatsapp.net":true,"212603342466@s.whatsapp.net":true,"212525151631@s.whatsapp.net":true,"212777383223@s.whatsapp.net":true,"212604794351@s.whatsapp.net":true,"212604425653@s.whatsapp.net":true,"212644908985@s.whatsapp.net":true,"212774109411@s.whatsapp.net":true,"212701709286@s.whatsapp.net":true,"255673947367@s.whatsapp.net":true,"212722934441@s.whatsapp.net":true,"212708412344@s.whatsapp.net":true,"212691032965@s.whatsapp.net":true,"212608103142@s.whatsapp.net":true,"212617377197@s.whatsapp.net":true,"212636836561@s.whatsapp.net":true,"212676084359@s.whatsapp.net":true,"212637218854@s.whatsapp.net":true,"212707780759@s.whatsapp.net":true,"212706753859@s.whatsapp.net":true,"212602646625@s.whatsapp.net":true,"212629000462@s.whatsapp.net":true,"212604137797@s.whatsapp.net":true,"212774971546@s.whatsapp.net":true,"212710045870@s.whatsapp.net":true,"212654265451@s.whatsapp.net":true,"212672750539@s.whatsapp.net":true,"212606288670@s.whatsapp.net":true,"212625612263@s.whatsapp.net":true,"212670379620@s.whatsapp.net":true,"212630417047@s.whatsapp.net":true,"212666469868@s.whatsapp.net":true,"212643033414@s.whatsapp.net":true,"212653466069@s.whatsapp.net":true,"212609321107@s.whatsapp.net":true,"212720885147@s.whatsapp.net":true,"212631774602@s.whatsapp.net":true,"212657319341@s.whatsapp.net":true,"212630193822@s.whatsapp.net":true,"201099622996@s.whatsapp.net":true,"212606074386@s.whatsapp.net":true,"212658587825@s.whatsapp.net":true,"212617952389@s.whatsapp.net":true,"212670304905@s.whatsapp.net":true,"212719942424@s.whatsapp.net":true,"212651852229@s.whatsapp.net":true,"27713456746@s.whatsapp.net":true,"212778795111@s.whatsapp.net":true,"212778367648@s.whatsapp.net":true,"212674456519@s.whatsapp.net":true,"212635957170@s.whatsapp.net":true,"212712973545@s.whatsapp.net":true,"212625680556@s.whatsapp.net":true,"212656818856@s.whatsapp.net":true,"212606788433@s.whatsapp.net":true,"212678954097@s.whatsapp.net":true,"212605834769@s.whatsapp.net":true,"212666204784@s.whatsapp.net":true,"212681249798@s.whatsapp.net":true,"212675962334@s.whatsapp.net":true,"212694329729@s.whatsapp.net":true,"212607705668@s.whatsapp.net":true,"212717257017@s.whatsapp.net":true,"212699662067@s.whatsapp.net":true,"212605473215@s.whatsapp.net":true,"212687321480@s.whatsapp.net":true,"212601251898@s.whatsapp.net":true,"212600883752@s.whatsapp.net":true,"212626314906@s.whatsapp.net":true,"212711280333@s.whatsapp.net":true,"212646117032@s.whatsapp.net":true,"212609176809@s.whatsapp.net":true,"212627029968@s.whatsapp.net":true,"212601482021@s.whatsapp.net":true,"212603481678@s.whatsapp.net":true,"212614638587@s.whatsapp.net":true,"212652031114@s.whatsapp.net":true,"212779306780@s.whatsapp.net":true,"212762182885@s.whatsapp.net":true,"212637673099@s.whatsapp.net":true,"212780422482@s.whatsapp.net":true,"212649223502@s.whatsapp.net":true,"212605087547@s.whatsapp.net":true,"212713005235@s.whatsapp.net":true,"212769557990@s.whatsapp.net":true,"212646264198@s.whatsapp.net":true,"212607131453@s.whatsapp.net":true,"212706818250@s.whatsapp.net":true,"212718957236@s.whatsapp.net":true,"212694767137@s.whatsapp.net":true,"212652032384@s.whatsapp.net":true,"212631815643@s.whatsapp.net":true,"212604761177@s.whatsapp.net":true,"212777032205@s.whatsapp.net":true,"212779759403@s.whatsapp.net":true,"212612181787@s.whatsapp.net":true,"212764082515@s.whatsapp.net":true,"212714106787@s.whatsapp.net":true,"212723864055@s.whatsapp.net":true,"212631550482@s.whatsapp.net":true,"212694163662@s.whatsapp.net":true,"212600195897@s.whatsapp.net":true,"212616640259@s.whatsapp.net":true,"212601562331@s.whatsapp.net":true,"212629002385@s.whatsapp.net":true,"212762434789@s.whatsapp.net":true,"212706793736@s.whatsapp.net":true,"212602988020@s.whatsapp.net":true,"212678373042@s.whatsapp.net":true,"212779488713@s.whatsapp.net":true,"212708658471@s.whatsapp.net":true,"212705139346@s.whatsapp.net":true,"212723731223@s.whatsapp.net":true,"212606177740@s.whatsapp.net":true,"212649811668@s.whatsapp.net":true,"212606882204@s.whatsapp.net":true,"212724616714@s.whatsapp.net":true,"212603478990@s.whatsapp.net":true,"212640855345@s.whatsapp.net":true,"212608509465@s.whatsapp.net":true,"212675528819@s.whatsapp.net":true,"212621907832@s.whatsapp.net":true,"212715014958@s.whatsapp.net":true,"212715014958:1@s.whatsapp.net":true,"212715014958:4@s.whatsapp.net":true,"212775662865@s.whatsapp.net":true,"212691264400@s.whatsapp.net":true,"212721371152@s.whatsapp.net":true,"212721369184@s.whatsapp.net":true,"212603831552@s.whatsapp.net":true,"212607344599@s.whatsapp.net":true,"212607344599:5@s.whatsapp.net":true,"212772473962@s.whatsapp.net":true,"212771210464@s.whatsapp.net":true,"212771684837@s.whatsapp.net":true,"212764375861@s.whatsapp.net":true,"212689650980@s.whatsapp.net":true,"212629085978@s.whatsapp.net":true,"212641391545@s.whatsapp.net":true,"212643387887@s.whatsapp.net":true,"212718444817@s.whatsapp.net":true,"212613049967@s.whatsapp.net":true,"212623656620@s.whatsapp.net":true,"212712825910@s.whatsapp.net":true,"967716615497@s.whatsapp.net":true,"212681204369@s.whatsapp.net":true,"212710643595@s.whatsapp.net":true,"212655886598@s.whatsapp.net":true,"212715090203@s.whatsapp.net":true,"212606491586@s.whatsapp.net":true,"212707933372@s.whatsapp.net":true,"212627197634@s.whatsapp.net":true,"212715610364@s.whatsapp.net":true,"212633382486@s.whatsapp.net":true,"212623856788@s.whatsapp.net":true,"212719141350@s.whatsapp.net":true,"212622155850@s.whatsapp.net":true,"212703633052@s.whatsapp.net":true,"212612170994@s.whatsapp.net":true,"212702233477@s.whatsapp.net":true,"212604425499@s.whatsapp.net":true,"212601607038@s.whatsapp.net":true,"212630820641@s.whatsapp.net":true,"212605344831@s.whatsapp.net":true,"212605093145@s.whatsapp.net":true,"212715198505@s.whatsapp.net":true,"212777222907@s.whatsapp.net":true,"212608583966@s.whatsapp.net":true,"212711813526@s.whatsapp.net":true,"212650136507@s.whatsapp.net":true,"212633873674@s.whatsapp.net":true,"212662891888@s.whatsapp.net":true,"212703230349@s.whatsapp.net":true,"212600531632@s.whatsapp.net":true,"212687825274@s.whatsapp.net":true,"212768585995@s.whatsapp.net":true,"212630749119@s.whatsapp.net":true,"212626952924@s.whatsapp.net":true,"212661448173@s.whatsapp.net":true,"212649156345@s.whatsapp.net":true,"212769420381@s.whatsapp.net":true,"212672364204@s.whatsapp.net":true,"212612258286@s.whatsapp.net":true,"212780753519@s.whatsapp.net":true,"212648627448@s.whatsapp.net":true,"212779952116@s.whatsapp.net":true,"212717524696@s.whatsapp.net":true,"212781412353@s.whatsapp.net":true,"212691823796@s.whatsapp.net":true,"212604644848@s.whatsapp.net":true,"212700726134@s.whatsapp.net":true,"212603293323@s.whatsapp.net":true,"212645134307@s.whatsapp.net":true,"212609531503@s.whatsapp.net":true,"212609531503:18@s.whatsapp.net":true,"212698200017@s.whatsapp.net":true,"212607092924@s.whatsapp.net":true,"212606320143@s.whatsapp.net":true,"212684492024@s.whatsapp.net":true,"212687661327@s.whatsapp.net":true,"212629323579@s.whatsapp.net":true,"212606212517@s.whatsapp.net":true,"212612401178@s.whatsapp.net":true,"212719301556@s.whatsapp.net":true,"212653510973@s.whatsapp.net":true,"212611305520@s.whatsapp.net":true,"212650251637@s.whatsapp.net":true,"212701748752@s.whatsapp.net":true,"212604920368@s.whatsapp.net":true,"212706380567@s.whatsapp.net":true,"212777437714@s.whatsapp.net":true,"212604143804@s.whatsapp.net":true,"212609443357@s.whatsapp.net":true,"212720142792@s.whatsapp.net":true,"212616490208@s.whatsapp.net":true,"212649144124@s.whatsapp.net":true,"212603356963@s.whatsapp.net":true,"212640762281@s.whatsapp.net":true,"212649928822@s.whatsapp.net":true,"212649928822:31@s.whatsapp.net":true,"212649928822:32@s.whatsapp.net":true,"212715993386@s.whatsapp.net":true,"212710559248@s.whatsapp.net":true,"212680477954@s.whatsapp.net":true,"212610118367@s.whatsapp.net":true,"212652324755@s.whatsapp.net":true,"212712821516@s.whatsapp.net":true,"212603123165@s.whatsapp.net":true,"212775329842@s.whatsapp.net":true,"212775329842:2@s.whatsapp.net":true,"212719689377@s.whatsapp.net":true,"212603859213@s.whatsapp.net":true,"212608714525@s.whatsapp.net":true,"212652648173@s.whatsapp.net":true,"212633104558@s.whatsapp.net":true,"212697990436@s.whatsapp.net":true,"212691680909@s.whatsapp.net":true,"212691680909:5@s.whatsapp.net":true,"212634256887@s.whatsapp.net":true,"212770707145@s.whatsapp.net":true,"212695358897@s.whatsapp.net":true,"212667732165@s.whatsapp.net":true,"212616328164@s.whatsapp.net":true,"212617423787@s.whatsapp.net":true,"212693237411@s.whatsapp.net":true,"212602193872@s.whatsapp.net":true,"212693489197@s.whatsapp.net":true,"212640684011@s.whatsapp.net":true,"212764436807@s.whatsapp.net":true,"212690511685@s.whatsapp.net":true,"212602454156@s.whatsapp.net":true,"212704727493@s.whatsapp.net":true,"212626079585@s.whatsapp.net":true,"212629066062@s.whatsapp.net":true,"212711557340@s.whatsapp.net":true,"212649630351@s.whatsapp.net":true,"212698831324@s.whatsapp.net":true,"212600317580@s.whatsapp.net":true,"212687874208@s.whatsapp.net":true,"212656657542@s.whatsapp.net":true,"212606120992@s.whatsapp.net":true,"212710757647@s.whatsapp.net":true,"212605396696@s.whatsapp.net":true,"212655450622@s.whatsapp.net":true,"212625694186@s.whatsapp.net":true,"212627631474@s.whatsapp.net":true,"212701188468@s.whatsapp.net":true,"212647316075@s.whatsapp.net":true,"212627613374@s.whatsapp.net":true,"212712740495@s.whatsapp.net":true,"212622061960@s.whatsapp.net":true,"212629467185@s.whatsapp.net":true,"212619139764@s.whatsapp.net":true,"212681161493@s.whatsapp.net":true,"212693496135@s.whatsapp.net":true,"212649713688@s.whatsapp.net":true,"212771905993@s.whatsapp.net":true,"212779679846@s.whatsapp.net":true,"212602229907@s.whatsapp.net":true,"212645890291@s.whatsapp.net":true,"212715194360@s.whatsapp.net":true,"212633545851@s.whatsapp.net":true,"212627776725@s.whatsapp.net":true,"212719036922@s.whatsapp.net":true,"212722748010@s.whatsapp.net":true,"212691300720@s.whatsapp.net":true,"212617796151@s.whatsapp.net":true,"212776262469@s.whatsapp.net":true,"212606445028@s.whatsapp.net":true,"212678566766@s.whatsapp.net":true,"212608942659@s.whatsapp.net":true,"212679258764@s.whatsapp.net":true,"212776314925@s.whatsapp.net":true,"212602520823@s.whatsapp.net":true,"212656212052@s.whatsapp.net":true,"212656212052:4@s.whatsapp.net":true,"212601227170@s.whatsapp.net":true,"212636461880@s.whatsapp.net":true,"212602807931@s.whatsapp.net":true,"212630757186@s.whatsapp.net":true,"212650176410@s.whatsapp.net":true,"212603801159@s.whatsapp.net":true,"212602791610@s.whatsapp.net":true,"212600107205@s.whatsapp.net":true,"212720734833@s.whatsapp.net":true,"212635393116@s.whatsapp.net":true,"212724217139@s.whatsapp.net":true,"212689618907@s.whatsapp.net":true,"212690596305@s.whatsapp.net":true,"212682044790@s.whatsapp.net":true,"212661209929@s.whatsapp.net":true,"212606647266@s.whatsapp.net":true,"212708147196@s.whatsapp.net":true,"212601365120@s.whatsapp.net":true,"212647490222@s.whatsapp.net":true,"212603566124@s.whatsapp.net":true,"212610871222@s.whatsapp.net":true,"212606916516@s.whatsapp.net":true,"212621282644@s.whatsapp.net":true,"212606613781@s.whatsapp.net":true,"212632162819@s.whatsapp.net":true,"212717977185@s.whatsapp.net":true,"212640845047@s.whatsapp.net":true,"212704514167@s.whatsapp.net":true,"201221448676@s.whatsapp.net":true,"212703142050@s.whatsapp.net":true,"212703142050:1@s.whatsapp.net":true,"212615148805@s.whatsapp.net":true,"212652328045@s.whatsapp.net":true,"212617371329@s.whatsapp.net":true,"212637069438@s.whatsapp.net":true,"212601111775@s.whatsapp.net":true,"212619476510@s.whatsapp.net":true,"212604149459@s.whatsapp.net":true,"212606278974@s.whatsapp.net":true,"212642498122@s.whatsapp.net":true,"923029737209@s.whatsapp.net":true,"212604844263@s.whatsapp.net":true,"212771605989@s.whatsapp.net":true,"212695466985@s.whatsapp.net":true,"212654252845@s.whatsapp.net":true,"212601742982@s.whatsapp.net":true,"34632353068@s.whatsapp.net":true,"212719963623@s.whatsapp.net":true,"212655310193@s.whatsapp.net":true,"212656094946@s.whatsapp.net":true,"212605574728@s.whatsapp.net":true,"212614857155@s.whatsapp.net":true,"212696298734@s.whatsapp.net":true,"212684768335@s.whatsapp.net":true,"212602334202@s.whatsapp.net":true,"212724289648@s.whatsapp.net":true,"212614119807@s.whatsapp.net":true,"212706265358@s.whatsapp.net":true,"249125579127@s.whatsapp.net":true,"212643868266@s.whatsapp.net":true,"212610360046@s.whatsapp.net":true,"212704866965@s.whatsapp.net":true,"212607597207@s.whatsapp.net":true,"212722221949@s.whatsapp.net":true,"212699636181@s.whatsapp.net":true,"212700479237@s.whatsapp.net":true,"212711931034@s.whatsapp.net":true,"212649134597@s.whatsapp.net":true,"212721652915@s.whatsapp.net":true,"212610293347@s.whatsapp.net":true,"212627135952@s.whatsapp.net":true,"212625539534@s.whatsapp.net":true,"212653649579@s.whatsapp.net":true,"201001594632@s.whatsapp.net":true,"212610796116@s.whatsapp.net":true,"212632605510@s.whatsapp.net":true,"212631981047@s.whatsapp.net":true,"212601121306@s.whatsapp.net":true,"212614339397@s.whatsapp.net":true,"212607409686@s.whatsapp.net":true,"212778785834@s.whatsapp.net":true,"212771070851@s.whatsapp.net":true,"212779978233@s.whatsapp.net":true,"212613579635@s.whatsapp.net":true,"212651652781@s.whatsapp.net":true,"212654226785@s.whatsapp.net":true,"212750783946@s.whatsapp.net":true,"212707025951@s.whatsapp.net":true,"212724279220@s.whatsapp.net":true,"201224070002@s.whatsapp.net":true,"212628430779@s.whatsapp.net":true,"212648486759@s.whatsapp.net":true,"212638581539@s.whatsapp.net":true,"212714829987@s.whatsapp.net":true,"212698164005@s.whatsapp.net":true,"212655106012@s.whatsapp.net":true,"255684883941@s.whatsapp.net":true,"212647062459@s.whatsapp.net":true,"212773084201@s.whatsapp.net":true,"212722981120@s.whatsapp.net":true,"212712105101@s.whatsapp.net":true,"212616772809@s.whatsapp.net":true,"212699617189@s.whatsapp.net":true,"212653967131@s.whatsapp.net":true,"212605570898@s.whatsapp.net":true,"212603663849@s.whatsapp.net":true,"212626900936@s.whatsapp.net":true,"212711602548@s.whatsapp.net":true,"212719075053@s.whatsapp.net":true,"212637362885@s.whatsapp.net":true,"212631917138@s.whatsapp.net":true,"212780756836@s.whatsapp.net":true,"212603460391@s.whatsapp.net":true,"212631975052@s.whatsapp.net":true,"212606759524@s.whatsapp.net":true,"212618837842@s.whatsapp.net":true,"212607929772@s.whatsapp.net":true,"212643068978@s.whatsapp.net":true,"212626681684@s.whatsapp.net":true,"212621092802@s.whatsapp.net":true,"212771095153@s.whatsapp.net":true,"212771095153:41@s.whatsapp.net":true,"212771095153:43@s.whatsapp.net":true,"212613420046@s.whatsapp.net":true,"212704332256@s.whatsapp.net":true,"212627065142@s.whatsapp.net":true,"212776591230@s.whatsapp.net":true,"27686770833@s.whatsapp.net":true,"212697582068@s.whatsapp.net":true,"212623142007@s.whatsapp.net":true,"212702695856@s.whatsapp.net":true,"201126054178@s.whatsapp.net":true,"212602964233@s.whatsapp.net":true,"212776783113@s.whatsapp.net":true,"212612544505@s.whatsapp.net":true,"212609498542@s.whatsapp.net":true,"212603704268@s.whatsapp.net":true,"212654872700@s.whatsapp.net":true,"212711956315@s.whatsapp.net":true,"212602180198@s.whatsapp.net":true,"212622204600@s.whatsapp.net":true,"212707724183@s.whatsapp.net":true,"212662425720@s.whatsapp.net":true,"212713011586@s.whatsapp.net":true,"212600545633@s.whatsapp.net":true,"212707398004@s.whatsapp.net":true,"212669775992@s.whatsapp.net":true,"212603542527@s.whatsapp.net":true,"923051038857@s.whatsapp.net":true,"212719907267@s.whatsapp.net":true,"212608556810@s.whatsapp.net":true,"212775592264@s.whatsapp.net":true,"212605799760@s.whatsapp.net":true,"212711241055@s.whatsapp.net":true,"212649016663@s.whatsapp.net":true,"212625695101@s.whatsapp.net":true,"212623349909@s.whatsapp.net":true,"212612651324@s.whatsapp.net":true,"212709691137@s.whatsapp.net":true,"212649236530@s.whatsapp.net":true,"212630165682@s.whatsapp.net":true,"212680697294@s.whatsapp.net":true,"212657405090@s.whatsapp.net":true,"212671136611@s.whatsapp.net":true,"212771184190@s.whatsapp.net":true,"212718916399@s.whatsapp.net":true,"212613389333@s.whatsapp.net":true,"212610882369@s.whatsapp.net":true,"212610882369:1@s.whatsapp.net":true,"212624716095@s.whatsapp.net":true,"212633019381@s.whatsapp.net":true,"212606450506@s.whatsapp.net":true,"33758410958@s.whatsapp.net":true,"212614825340@s.whatsapp.net":true,"93792232233@s.whatsapp.net":true,"212716174060@s.whatsapp.net":true,"212718431791@s.whatsapp.net":true,"212777384143@s.whatsapp.net":true,"212638140511@s.whatsapp.net":true,"212627823440@s.whatsapp.net":true,"212627333169@s.whatsapp.net":true,"212719543214@s.whatsapp.net":true,"212617948224@s.whatsapp.net":true,"212716313064@s.whatsapp.net":true,"212691247991@s.whatsapp.net":true,"212605767591@s.whatsapp.net":true,"212647732999@s.whatsapp.net":true,"212695095601@s.whatsapp.net":true,"212601170488@s.whatsapp.net":true,"212632678054@s.whatsapp.net":true,"212603859640@s.whatsapp.net":true,"212779785239@s.whatsapp.net":true,"212647287524@s.whatsapp.net":true,"212608949894@s.whatsapp.net":true,"212606646072@s.whatsapp.net":true,"212677859071@s.whatsapp.net":true,"212612217593@s.whatsapp.net":true,"212687737895@s.whatsapp.net":true,"212681898733@s.whatsapp.net":true,"212627651209@s.whatsapp.net":true,"34646907377@s.whatsapp.net":true,"212611736275@s.whatsapp.net":true,"212677313056@s.whatsapp.net":true,"212632095564@s.whatsapp.net":true,"212655178897@s.whatsapp.net":true,"212676212925@s.whatsapp.net":true,"212640145384@s.whatsapp.net":true,"212717403493@s.whatsapp.net":true,"212653685372@s.whatsapp.net":true,"212650532268@s.whatsapp.net":true,"212645631820@s.whatsapp.net":true,"212603931875@s.whatsapp.net":true,"212600140727@s.whatsapp.net":true,"212716189051@s.whatsapp.net":true,"212606155685@s.whatsapp.net":true,"212695387491@s.whatsapp.net":true,"212633564948@s.whatsapp.net":true,"212613172614@s.whatsapp.net":true,"212604034199@s.whatsapp.net":true,"212775228515@s.whatsapp.net":true,"212779996300@s.whatsapp.net":true,"212660414139@s.whatsapp.net":true,"212633632391@s.whatsapp.net":true,"212605199780@s.whatsapp.net":true,"212678229275@s.whatsapp.net":true,"212635251228@s.whatsapp.net":true,"212709307460@s.whatsapp.net":true,"212694825221@s.whatsapp.net":true,"212621174874@s.whatsapp.net":true,"212606467170@s.whatsapp.net":true,"212698316609@s.whatsapp.net":true,"212628719068@s.whatsapp.net":true,"212691227432@s.whatsapp.net":true,"212687617825@s.whatsapp.net":true,"212664377191@s.whatsapp.net":true,"33612755471@s.whatsapp.net":true,"212660580060@s.whatsapp.net":true,"212627619458@s.whatsapp.net":true,"212714153321@s.whatsapp.net":true,"212687481598@s.whatsapp.net":true,"212601838941@s.whatsapp.net":true,"212699061776@s.whatsapp.net":true,"212714890609@s.whatsapp.net":true,"212606866748@s.whatsapp.net":true,"212606087255@s.whatsapp.net":true,"212601006741@s.whatsapp.net":true,"212600362974@s.whatsapp.net":true,"212709617908@s.whatsapp.net":true}